rediscache_cachetools/__init__.py
rediscache_cachetools/cached.py
rediscache_cachetools/chain_cache.py
rediscache_cachetools/redis_cache.py
rediscache_cachetools-0.2.0.dist-info/METADATA
rediscache_cachetools-0.2.0.dist-info/WHEEL
rediscache_cachetools-0.2.0.dist-info/RECORD
